Metadata-Version: 1.1
Name: bookpam
Version: 0.0.1
Summary: BookPam is a typesetting system; it includes features designed for the production of technical documentation and book.
Home-page: https://maxbase.org/
Author: Max Base
Author-email: maxbasecode@gmail.com
License: GNU GENERAL PUBLIC LICENSE
Keywords: bookpam
Platform: UNKNOWN
Classifier: Development Status :: 5 - Production/Stable
Classifier: Intended Audience :: Education
Classifier: Operating System :: Microsoft :: Windows :: Windows 10
Classifier: License :: OSI Approved :: MIT License
Classifier: Programming Language :: Python :: 3
